LICENSE
abnex/__init__.py
abnex-1.0.2.dist-info/LICENSE
abnex-1.0.2.dist-info/WHEEL
abnex-1.0.2.dist-info/METADATA
abnex-1.0.2.dist-info/RECORD
