Metadata-Version: 2.1
Name: abnex
Version: 1.0.2
Summary: Abnormal expressions (abnex) is an alternative to regular expressions (regex).
Home-page: https://github.com/Buscedv/abnormal-expressions
License: GNU GPL v3.0
Keywords: pattern matching,text,regex,abnex,regular expressions,abnormal expressions
Author: Edvard Busck-Nielsen
Author-email: me@edvard.dev
Requires-Python: >=3.8,<4.0
Classifier: License :: OSI Approved :: GNU General Public License v3 or later (GPLv3+)
Classifier: License :: Other/Proprietary License
Classifier: Operating System :: OS Independent
Classifier: Programming Language :: Python :: 3
Classifier: Programming Language :: Python :: 3.8
Classifier: Programming Language :: Python :: 3.9
Classifier: Topic :: Software Development
Project-URL: Repository, https://github.com/Buscedv/abnormal-expressions
